MANIFEST.in
requirements.txt
setup.py
plush/__init__.py
plush/application.py
plush/backend.py
plush/command.py
plush/conf.py
plush/decorators.py
plush/deferred.py
plush/registry.py
plush/request.py
plush/response.py
plush/server.py
plush/testing.py
plush/util/__init__.py
plush/util/http.py
plush/util/iter.py
plush/util/lang.py
plush/util/compat/__init__.py
plush/util/compat/importlib.py
plush_web.egg-info/PKG-INFO
plush_web.egg-info/SOURCES.txt
plush_web.egg-info/dependency_links.txt
plush_web.egg-info/requires.txt
plush_web.egg-info/top_level.txt
test/test_conf.py
test/test_registry.py
test/test_request.py
test/test_response.py