Metadata-Version: 1.0
Name: plush-web
Version: 0.1.0
Summary: Micro framework inspirated by Sinatra, Express and Flask.
Home-page: https://github.com/gsamokovarov/plush
Author: Genadi Samokovarov
Author-email: gsamokovarov@gmail.com
License: http://www.apache.org/licenses/LICENSE-2.0
Download-URL: https://github.com/gsamokovarov/plush/tarball/0.1.0
Platform: UNKNOWN
